pkg/orchestrator/specs/dataset/source/ui_dialog/adls_source_spec.py
pkg/orchestrator/specs/dataset/source/ui_dialog/bigquery_source_spec.py
pkg/orchestrator/specs/dataset/source/ui_dialog/databricks_source_spec.py
pkg/orchestrator/specs/dataset/source/ui_dialog/databricks_volume_source_spec.py
pkg/orchestrator/specs/dataset/source/ui_dialog/duckdb_source_spec.py
pkg/orchestrator/specs/dataset/source/ui_dialog/gcs_source_spec.py
pkg/orchestrator/specs/dataset/source/ui_dialog/hana_source_spec.py
pkg/orchestrator/specs/dataset/source/ui_dialog/minion_source_spec.py
pkg/orchestrator/specs/dataset/source/ui_dialog/mongodb_source_spec.py
pkg/orchestrator/specs/dataset/source/ui_dialog/mssql_source_spec.py
pkg/orchestrator/specs/dataset/source/ui_dialog/onedrive_source_spec.py
pkg/orchestrator/specs/dataset/source/ui_dialog/oracle_source_spec.py
pkg/orchestrator/specs/dataset/source/ui_dialog/preview_table_spec.py
pkg/orchestrator/specs/dataset/source/ui_dialog/redshift_source_spec.py
pkg/orchestrator/specs/dataset/source/ui_dialog/s3_source_spec.py
pkg/orchestrator/specs/dataset/source/ui_dialog/salesforce_source_spec.py
pkg/orchestrator/specs/dataset/source/ui_dialog/sftp_source_spec.py
pkg/orchestrator/specs/dataset/source/ui_dialog/sharepoint_source_spec.py
pkg/orchestrator/specs/dataset/source/ui_dialog/smartsheet_source_spec.py
pkg/orchestrator/specs/dataset/source/ui_dialog/snowflake_source_spec.py
pkg/orchestrator/specs/dataset/source/ui_dialog/synapse_source_spec.py
pkg/orchestrator/specs/dataset/target/ui_dialog/adls_target_spec.py
pkg/orchestrator/specs/dataset/target/ui_dialog/bigquery_target_spec.py
pkg/orchestrator/specs/dataset/target/ui_dialog/databricks_target_spec.py
pkg/orchestrator/specs/dataset/target/ui_dialog/databricks_volume_target_spec.py
pkg/orchestrator/specs/dataset/target/ui_dialog/duckdb_target_spec.py
pkg/orchestrator/specs/dataset/target/ui_dialog/gcs_target_spec.py
pkg/orchestrator/specs/dataset/target/ui_dialog/hana_target_spec.py
prophecy_automate-1.0.0.dev1.dist-info/licenses/LICENSE
prophecy_automate-1.0.0.dev1.dist-info/METADATA
prophecy_automate-1.0.0.dev1.dist-info/WHEEL
prophecy_automate-1.0.0.dev1.dist-info/top_level.txt
prophecy_automate-1.0.0.dev1.dist-info/RECORD
